odoo/addons/l10n_it_asset_history_import/README.rst
odoo/addons/l10n_it_asset_history_import/__init__.py
odoo/addons/l10n_it_asset_history_import/__manifest__.py
odoo/addons/l10n_it_asset_history_import/i18n/it.po
odoo/addons/l10n_it_asset_history_import/i18n/l10n_it_asset_history_import.pot
odoo/addons/l10n_it_asset_history_import/models/__init__.py
odoo/addons/l10n_it_asset_history_import/models/asset.py
odoo/addons/l10n_it_asset_history_import/models/asset_category.py
odoo/addons/l10n_it_asset_history_import/models/asset_depreciation_line.py
odoo/addons/l10n_it_asset_history_import/models/asset_depreciation_mode.py
odoo/addons/l10n_it_asset_history_import/models/asset_depreciation_type.py
odoo/addons/l10n_it_asset_history_import/readme/DESCRIPTION.rst
odoo/addons/l10n_it_asset_history_import/readme/USAGE.rst
odoo/addons/l10n_it_asset_history_import/security/ir.model.access.csv
odoo/addons/l10n_it_asset_history_import/static/asset_import.png
odoo/addons/l10n_it_asset_history_import/static/description/icon.png
odoo/addons/l10n_it_asset_history_import/static/description/index.html
odoo/addons/l10n_it_asset_history_import/views/asset.xml
odoo/addons/l10n_it_asset_history_import/views/asset_category.xml
odoo/addons/l10n_it_asset_history_import/views/asset_depreciation_mode.xml
odoo/addons/l10n_it_asset_history_import/views/asset_depreciation_type.xml
odoo/addons/l10n_it_asset_history_import/wizards/__init__.py
odoo/addons/l10n_it_asset_history_import/wizards/asset_history_import.py
odoo/addons/l10n_it_asset_history_import/wizards/asset_history_import.xml
odoo14_addon_l10n_it_asset_history_import-14.0.1.0.1.dev10.dist-info/METADATA
odoo14_addon_l10n_it_asset_history_import-14.0.1.0.1.dev10.dist-info/WHEEL
odoo14_addon_l10n_it_asset_history_import-14.0.1.0.1.dev10.dist-info/top_level.txt
odoo14_addon_l10n_it_asset_history_import-14.0.1.0.1.dev10.dist-info/RECORD
